mkdocs_asyncapi_plugin.py
mkdocs_asyncapi_plugin-0.2.0.dist-info/entry_points.txt
mkdocs_asyncapi_plugin-0.2.0.dist-info/LICENSE
mkdocs_asyncapi_plugin-0.2.0.dist-info/WHEEL
mkdocs_asyncapi_plugin-0.2.0.dist-info/METADATA
mkdocs_asyncapi_plugin-0.2.0.dist-info/RECORD
