Metadata-Version: 2.1
Name: mkdocs-asyncapi-plugin
Version: 0.2.0
Summary: mkdocs plugin to generate pages from asyncapi spec files
Home-page: https://github.com/yushiomote/mkdocs-asyncapi-plugin
License: MIT
Keywords: mkdocs,asyncapi,plugin,python
Author: YushiOMOTE
Author-email: yushiomote@gmail.com
Requires-Python: >=3.7
Classifier: Development Status :: 3 - Alpha
Classifier: Intended Audience :: Developers
Classifier: License :: OSI Approved :: MIT License
Classifier: Operating System :: OS Independent
Classifier: Programming Language :: Python :: 3
Classifier: Programming Language :: Python :: 3.7
Classifier: Programming Language :: Python :: 3.8
Classifier: Programming Language :: Python :: 3.9
Project-URL: Documentation, https://github.com/yushiomote/mkdocs-asyncapi-plugin
Project-URL: Repository, https://github.com/yushiomote/mkdocs-asyncapi-plugin
